amp_tools/__init__.py
amp_tools/constants.py
amp_tools/utils.py
amp_tools/tests/__init__.py
amp_tools/tests/test_transform_html_to_amp_class.py
amp_tools/tests/utils.py
amp_tools-0.0.4.dist-info/LICENSE
amp_tools-0.0.4.dist-info/METADATA
amp_tools-0.0.4.dist-info/WHEEL
amp_tools-0.0.4.dist-info/top_level.txt
amp_tools-0.0.4.dist-info/RECORD
